astrocytes/__init__.py
astrocytes/schema.py
astrocytes/_datasets/__init__.py
astrocytes/_datasets/_bath_application.py
astrocytes/_datasets/_common.py
astrocytes/_datasets/_embeddings.py
astrocytes/_datasets/_future.py
astrocytes/_datasets/_uncaging.py
astrocytes/backend/__init__.py
astrocytes/backend/embed.py
astrocytes/backend/pca.py
astrocytes-0.1.1a4.dist-info/METADATA
astrocytes-0.1.1a4.dist-info/WHEEL
astrocytes-0.1.1a4.dist-info/entry_points.txt
astrocytes-0.1.1a4.dist-info/RECORD
