Metadata-Version: 2.4
Name: astrocytes
Version: 0.1.1a4
Summary: TODO
Author-email: Maxine Levesque <170461181+maxinelevesque@users.noreply.github.com>
Requires-Python: <3.14,>=3.12
Requires-Dist: asyncstdlib>=3.13.1
Requires-Dist: atdata>=0.1.2b1
Requires-Dist: matplotlib>=3.10.7
Requires-Dist: python-dotenv>=1.2.1
Requires-Dist: scikit-image>=0.25.2
Requires-Dist: scikit-learn>=1.7.2
Requires-Dist: scipy>=1.16.3
Requires-Dist: toile>=0.1.1a2
